MANIFEST.in
account_chart.xml
account_tax_code_template.xml
account_tax_template.xml
l10n_chart_ro_wizard.xml
partner_view.xml
setup.py
./__init__.py
./__openerp__.py
./res_partner.py
images/config_chart_l10n_ro.jpeg
images/l10n_ro_chart.jpeg
openerp_l10n_ro.egg-info/PKG-INFO
openerp_l10n_ro.egg-info/SOURCES.txt
openerp_l10n_ro.egg-info/dependency_links.txt
openerp_l10n_ro.egg-info/requires.txt
openerp_l10n_ro.egg-info/top_level.txt
static/src/img/icon.png